python_frank_energie/__init__.py
python_frank_energie/authentication.py
python_frank_energie/exceptions.py
python_frank_energie/frank_energie.py
python_frank_energie/models.py
python_frank_energie/time_periods.py
python_frank_energie-2025.12.29.dist-info/METADATA
python_frank_energie-2025.12.29.dist-info/WHEEL
python_frank_energie-2025.12.29.dist-info/licenses/LICENSE
python_frank_energie-2025.12.29.dist-info/RECORD
