Metadata-Version: 2.4
Name: python-frank-energie
Version: 2025.12.29
Summary: Asynchronous Python client for the Frank Energie
License: Apache-2.0
License-File: LICENSE
Author: HiDiHo01
Maintainer: HiDiHo01
Requires-Python: >=3.10,<4.0
Classifier: License :: OSI Approved :: Apache Software License
Classifier: Operating System :: OS Independent
Classifier: Programming Language :: Python :: 3
Classifier: Programming Language :: Python :: 3.10
Classifier: Programming Language :: Python :: 3.11
Classifier: Programming Language :: Python :: 3.12
Classifier: Programming Language :: Python :: 3.13
Classifier: Programming Language :: Python :: 3.14
Requires-Dist: PyJWT (>=2.10.1,<3.0.0)
Requires-Dist: aiohttp (>=3.8.4,<6.0.0)
Requires-Dist: cffi (>=2.0.0,<3.0.0)
Requires-Dist: cryptography (>=44.0.1,<47.0.0)
Requires-Dist: propcache (>=0.3.0,<0.5.0)
Requires-Dist: python-dateutil (>=2.9.0,<3.0.0)
Requires-Dist: pytz (>=2025.2,<2026.0)
Requires-Dist: requests (>=2.32.5,<3.0.0)
Requires-Dist: six (>=1.17.0,<2.0.0)
Requires-Dist: syrupy (>=4.9.1,<6.0.0)
Project-URL: Bug Tracker, https://github.com/HiDiHo01/python-frank-energie/issues
Project-URL: Changelog, https://github.com/HiDiHo01/python-frank-energie/releases
Project-URL: Documentation, https://github.com/HiDiHo01/python-frank-energie
Project-URL: Homepage, https://github.com/HiDiHo01/python-frank-energie
Project-URL: Repository, https://github.com/HiDiHo01/python-frank-energie
